Font/__init__.py
Font/character.py
Font/config.py
Font/funcs.py
Font/render.py
Font-1.1.1.dist-info/LICENSE
Font-1.1.1.dist-info/METADATA
Font-1.1.1.dist-info/WHEEL
Font-1.1.1.dist-info/top_level.txt
Font-1.1.1.dist-info/RECORD
